pycdsl/__init__.py
pycdsl/cli.py
pycdsl/constants.py
pycdsl/corpus.py
pycdsl/lexicon.py
pycdsl/models.py
pycdsl/shell.py
pycdsl/utils.py
PyCDSL-0.9.0.dist-info/AUTHORS.rst
PyCDSL-0.9.0.dist-info/LICENSE
PyCDSL-0.9.0.dist-info/METADATA
PyCDSL-0.9.0.dist-info/WHEEL
PyCDSL-0.9.0.dist-info/entry_points.txt
PyCDSL-0.9.0.dist-info/top_level.txt
PyCDSL-0.9.0.dist-info/RECORD
