Metadata-Version: 2.1
Name: PyCDSL
Version: 0.9.0
Summary: Access various dictionaries from CDSL (Cologne Digital Sanskrit Lexicon)
Home-page: https://github.com/hrishikeshrt/PyCDSL
Author: Hrishikesh Terdalkar
Author-email: hrishikeshrt@linuxmail.org
License: GNU General Public License v3
Keywords: pycdsl,sanskrit,lexicon,dictionary
Platform: UNKNOWN
Classifier: Development Status :: 4 - Beta
Classifier: Intended Audience :: Developers
Classifier: Intended Audience :: Education
Classifier: License :: OSI Approved :: GNU General Public License v3 (GPLv3)
Classifier: Natural Language :: English
Classifier: Topic :: Scientific/Engineering
Classifier: Topic :: Text Processing :: Linguistic
Classifier: Topic :: Text Processing :: Markup
Classifier: Topic :: Utilities
Classifier: Programming Language :: Python :: 3
Classifier: Programming Language :: Python :: 3.6
Classifier: Programming Language :: Python :: 3.7
Classifier: Programming Language :: Python :: 3.8
Classifier: Programming Language :: Python :: 3.9
Requires-Python: >=3.6
License-File: LICENSE
License-File: AUTHORS.rst
Requires-Dist: requests (>=2.26.0)
Requires-Dist: requests-downloader (>=0.2.3)
Requires-Dist: beautifulsoup4 (>=4.10.0)
Requires-Dist: lxml (>=4.6.2)
Requires-Dist: peewee (>=3.14.4)
Requires-Dist: indic-transliteration (>=2.2.4)
Requires-Dist: cmd2 (>=2.4.1)
Requires-Dist: pyreadline3 ; platform_system == "Windows"
